onsapi/OnsApiClient.py
onsapi/OnsDataset.py
onsapi/__init__.py
onsapi-0.2.2.dist-info/METADATA
onsapi-0.2.2.dist-info/WHEEL
onsapi-0.2.2.dist-info/licenses/LICENSE
onsapi-0.2.2.dist-info/RECORD
