Metadata-Version: 2.1
Name: onsapi
Version: 0.2.2
Summary: A package for interacting with the UK Office for National Statistics' Beta API.
Project-URL: Homepage, https://github.com/Pooleyo/onsapi
Project-URL: Issues, https://github.com/Pooleyo/onsapi/issues
Author-email: Ashley Poole <apoole@tcd.ie>
License-File: LICENSE
Classifier: License :: OSI Approved :: Apache Software License
Classifier: Operating System :: OS Independent
Classifier: Programming Language :: Python :: 3
Requires-Python: >=3.8
Requires-Dist: pandas
Requires-Dist: pydantic
Requires-Dist: requests
